arb_launcher/__init__.py
arb_launcher/cli.py
arb_launcher/launcher.py
arb_launcher/program_handler.py
arb_launcher-1.1.0.dist-info/METADATA
arb_launcher-1.1.0.dist-info/WHEEL
arb_launcher-1.1.0.dist-info/entry_points.txt
arb_launcher-1.1.0.dist-info/top_level.txt
arb_launcher-1.1.0.dist-info/RECORD
