Metadata-Version: 2.1
Name: arb-launcher
Version: 1.1.0
Summary: A package to launch and manage detached programs
Home-page: https://github.com/Acid3croco/arb-trops-services
Author: arb
Author-email: arb.trops@gmail.com
Requires-Dist: setproctitle
Requires-Dist: arb-logger
Requires-Dist: psutil
